odoo/addons/hr_expense_due_date/README.rst
odoo/addons/hr_expense_due_date/__init__.py
odoo/addons/hr_expense_due_date/__manifest__.py
odoo/addons/hr_expense_due_date/i18n/hr_expense_due_date.pot
odoo/addons/hr_expense_due_date/i18n/it.po
odoo/addons/hr_expense_due_date/i18n/pt.po
odoo/addons/hr_expense_due_date/i18n/pt_BR.po
odoo/addons/hr_expense_due_date/models/__init__.py
odoo/addons/hr_expense_due_date/models/hr_expense.py
odoo/addons/hr_expense_due_date/models/hr_expense_sheet.py
odoo/addons/hr_expense_due_date/readme/CONTRIBUTORS.rst
odoo/addons/hr_expense_due_date/readme/DESCRIPTION.rst
odoo/addons/hr_expense_due_date/readme/USAGE.rst
odoo/addons/hr_expense_due_date/static/description/icon.png
odoo/addons/hr_expense_due_date/static/description/index.html
odoo/addons/hr_expense_due_date/tests/__init__.py
odoo/addons/hr_expense_due_date/tests/test_hr_expense_sheet.py
odoo/addons/hr_expense_due_date/views/hr_expense_sheet.xml
odoo14_addon_hr_expense_due_date-14.0.1.0.1.dev8.dist-info/METADATA
odoo14_addon_hr_expense_due_date-14.0.1.0.1.dev8.dist-info/WHEEL
odoo14_addon_hr_expense_due_date-14.0.1.0.1.dev8.dist-info/top_level.txt
odoo14_addon_hr_expense_due_date-14.0.1.0.1.dev8.dist-info/RECORD
